tmd/__init__.py
tmd/utils.py
tmd/Neuron/Neuron.py
tmd/Neuron/__init__.py
tmd/Neuron/methods.py
tmd/Population/Population.py
tmd/Population/__init__.py
tmd/Soma/Soma.py
tmd/Soma/__init__.py
tmd/Soma/methods.py
tmd/Topology/__init__.py
tmd/Topology/analysis.py
tmd/Topology/distances.py
tmd/Topology/methods.py
tmd/Topology/persistent_properties.py
tmd/Topology/statistics.py
tmd/Topology/transformations.py
tmd/Topology/vectorizations.py
tmd/Tree/Tree.py
tmd/Tree/__init__.py
tmd/Tree/methods.py
tmd/io/__init__.py
tmd/io/conversion.py
tmd/io/h5.py
tmd/io/io.py
tmd/io/swc.py
tmd/view/__init__.py
tmd/view/common.py
tmd/view/plot.py
tmd/view/view.py
TMD-2.4.3.dist-info/AUTHORS.md
TMD-2.4.3.dist-info/LICENSE-BSD.txt
TMD-2.4.3.dist-info/LICENSE-LGPL.txt
TMD-2.4.3.dist-info/METADATA
TMD-2.4.3.dist-info/WHEEL
TMD-2.4.3.dist-info/top_level.txt
TMD-2.4.3.dist-info/RECORD
