Metadata-Version: 2.1
Name: TMD
Version: 2.4.3
Summary: A python package for the topological analysis of neurons.
Home-page: https://TMD.readthedocs.io
Author: Blue Brain Project, EPFL
License: GNU Lesser General Public License v3.0
Project-URL: Tracker, https://github.com/BlueBrain/TMD/issues
Project-URL: Source, https://github.com/BlueBrain/TMD
Classifier: Development Status :: 4 - Beta
Classifier: Intended Audience :: Education
Classifier: Intended Audience :: Science/Research
Classifier: Programming Language :: Python
Classifier: Programming Language :: Python :: 3
Classifier: Programming Language :: Python :: 3.8
Classifier: Programming Language :: Python :: 3.9
Classifier: Programming Language :: Python :: 3.10
Classifier: Programming Language :: Python :: 3.11
Classifier: Topic :: Scientific/Engineering :: Bio-Informatics
Requires-Python: >=3.8
License-File: LICENSE-BSD.txt
License-File: LICENSE-LGPL.txt
License-File: AUTHORS.md
Requires-Dist: h5py>=2.9.0
Requires-Dist: scipy>=1.4.0
Requires-Dist: numpy>=1.18.0
Requires-Dist: scikit-learn>=0.22.0
Requires-Dist: munkres>=1.0.12
Requires-Dist: cached-property>=1.5.1
Requires-Dist: morphio<4,>=3.3.4
Provides-Extra: docs
Requires-Dist: m2r2; extra == "docs"
Requires-Dist: sphinx; extra == "docs"
Requires-Dist: sphinx-bluebrain-theme; extra == "docs"
Requires-Dist: sphinx-click; extra == "docs"
Requires-Dist: docutils<0.21; extra == "docs"
Provides-Extra: test
Requires-Dist: mock>=3; extra == "test"
Requires-Dist: pytest>=6; extra == "test"
Requires-Dist: pytest-cov>=3; extra == "test"
Requires-Dist: pytest-html>=2; extra == "test"
Provides-Extra: viewer
Requires-Dist: matplotlib>=3.2.0; extra == "viewer"
